django_tables2_bulma_template/__init__.py
django_tables2_bulma_template/templates/django-tables2/bulma.html
django_tables2_bulma_template/templatetags/__init__.py
django_tables2_bulma_template/templatetags/django_tables2_bulma_template.py
tests/__init__.py
tests/settings.py
tests/test_bulma.py
tests/urls.py
django_tables2_bulma_template-0.2.0.dist-info/LICENSE.txt
django_tables2_bulma_template-0.2.0.dist-info/METADATA
django_tables2_bulma_template-0.2.0.dist-info/WHEEL
django_tables2_bulma_template-0.2.0.dist-info/top_level.txt
django_tables2_bulma_template-0.2.0.dist-info/RECORD
